{"kind":"article","variants":[{"traits":[{"interfaceLanguage":"swift"}],"paths":["\/documentation\/wwdcnotes\/wwdc24-10118-whats-new-in-uikit"]}],"hierarchy":{"paths":[["doc:\/\/WWDCNotes\/documentation\/WWDCNotes","doc:\/\/WWDCNotes\/documentation\/WWDCNotes\/WWDC24"]]},"sampleCodeDownload":{"kind":"sampleDownload","action":{"type":"reference","overridingTitle":"Watch Video (21 min)","identifier":"https:\/\/developer.apple.com\/wwdc24\/10118","isActive":true}},"abstract":[{"text":"Explore everything new in UIKit, including tab and document launch experiences, transitions, and text and input changes. We’ll also discuss better-than-ever interoperability between UIKit and SwiftUI animations and gestures, as well as general improvements throughout UIKit.","type":"text"}],"identifier":{"interfaceLanguage":"swift","url":"doc:\/\/WWDCNotes\/documentation\/WWDCNotes\/WWDC24-10118-Whats-new-in-UIKit"},"primaryContentSections":[{"kind":"content","content":[{"text":"Key features","type":"heading","level":1,"anchor":"Key-features"},{"text":"Document launch experience","type":"heading","level":2,"anchor":"Document-launch-experience"},{"items":[{"content":[{"inlineContent":[{"type":"text","text":"The launch experience for document-based apps has been redesigned"}],"type":"paragraph"}]},{"content":[{"inlineContent":[{"text":"Get full control over the launch view’s design","type":"text"}],"type":"paragraph"}]},{"content":[{"type":"paragraph","inlineContent":[{"text":"To learn more, watch ","type":"text"},{"isActive":true,"type":"reference","identifier":"https:\/\/developer.apple.com\/wwdc24\/10132"}]}]}],"type":"unorderedList"},{"type":"paragraph","inlineContent":[{"type":"image","identifier":"document-launch-experience"}]},{"text":"Tabs and sidebars","type":"heading","level":2,"anchor":"Tabs-and-sidebars"},{"items":[{"content":[{"inlineContent":[{"type":"text","text":"on iPadOS, tab bars have visual updates and have more customization features"}],"type":"paragraph"}]},{"content":[{"type":"paragraph","inlineContent":[{"type":"text","text":"The new compact look reduces empty space"}]}]},{"content":[{"inlineContent":[{"text":"Combined tab bar and sidebar experience","type":"text"}],"type":"paragraph"},{"items":[{"content":[{"type":"paragraph","inlineContent":[{"text":"See new ","type":"text"},{"code":"UITabBarController","type":"codeVoice"},{"text":" APIs","type":"text"}]}]}],"type":"unorderedList"}]},{"content":[{"type":"paragraph","inlineContent":[{"type":"text","text":"The sidebar and tab bar can be personalized by the user using drag and drop"}]},{"type":"unorderedList","items":[{"content":[{"type":"paragraph","inlineContent":[{"type":"text","text":"See new "},{"type":"codeVoice","code":"UITab"},{"type":"text","text":" and "},{"type":"codeVoice","code":"UITabGroup"},{"type":"text","text":" APIs"}]}]}]}]},{"content":[{"inlineContent":[{"text":"Native experience on both Mac Catalyst and visionOS","type":"text"}],"type":"paragraph"}]},{"content":[{"inlineContent":[{"type":"text","text":"Watch "},{"type":"reference","identifier":"https:\/\/developer.apple.com\/wwdc24\/10147","isActive":true}],"type":"paragraph"}]}],"type":"unorderedList"},{"text":"Fluid transitions","type":"heading","level":2,"anchor":"Fluid-transitions"},{"items":[{"content":[{"inlineContent":[{"type":"text","text":"On iOS 18, there is a new zoom transition"}],"type":"paragraph"}]},{"content":[{"inlineContent":[{"text":"It works with navigation and presentations","type":"text"}],"type":"paragraph"}]},{"content":[{"inlineContent":[{"text":"The transition is fully reversible and interruptible","type":"text"}],"type":"paragraph"}]}],"type":"unorderedList"},{"text":"SwiftUI interoperability","type":"heading","level":1,"anchor":"SwiftUI-interoperability"},{"text":"Animations","type":"heading","level":2,"anchor":"Animations"},{"items":[{"content":[{"inlineContent":[{"text":"You can now use SwiftUI animations to animate UIKit views","type":"text"}],"type":"paragraph"}]}],"type":"unorderedList"},{"type":"codeListing","syntax":"swift","code":["UIView.animate(.spring(duration: 0.5)) { ... }"]},{"items":[{"content":[{"type":"paragraph","inlineContent":[{"text":"Includes SwiftUI custom animations","type":"text"}]}]},{"content":[{"inlineContent":[{"text":"Can be used to animate views with gestures","type":"text"}],"type":"paragraph"},{"items":[{"content":[{"type":"paragraph","inlineContent":[{"type":"text","text":"To do this, animate both when the gesture changes and when it ends"}]}]}],"type":"unorderedList"}]}],"type":"unorderedList"},{"type":"codeListing","syntax":"swift","code":["switch gesture.state {","case .changed:","    UIView.animate(.interactiveSpring) { ... }","case .ended:","    UIView.animate(.spring) { ... }","}"]},{"text":"Gesture recognizers","type":"heading","level":2,"anchor":"Gesture-recognizers"},{"items":[{"content":[{"type":"paragraph","inlineContent":[{"text":"The gesture systems have been unified across SwiftUI and UIKit","type":"text"}]}]},{"content":[{"type":"paragraph","inlineContent":[{"text":"Support for coordination between gestures across both frameworks","type":"text"}]}]}],"type":"unorderedList"},{"text":"Refer to SwiftUI gestures in UIKit","type":"heading","level":3,"anchor":"Refer-to-SwiftUI-gestures-in-UIKit"},{"items":[{"content":[{"inlineContent":[{"text":"Specify a name when setting up your SwiftUI gesture","type":"text"}],"type":"paragraph"}]}],"type":"unorderedList"},{"type":"codeListing","syntax":"swift","code":["SomeView()","    .gesture(doubleTap, name: \"SwiftUIDoubleTap\")"]},{"items":[{"content":[{"type":"paragraph","inlineContent":[{"text":"In UIKit, check the name associated with a ","type":"text"},{"code":"UIGestureRecognizer","type":"codeVoice"}]}]},{"content":[{"type":"paragraph","inlineContent":[{"text":"This can, for example, be used to set up failure cases for SwiftUI animations in UIKit","type":"text"}]}]}],"type":"unorderedList"},{"text":"Add UIKit gesture recognizers to SwiftUI","type":"heading","level":3,"anchor":"Add-UIKit-gesture-recognizers-to-SwiftUI"},{"items":[{"content":[{"inlineContent":[{"text":"Adopt new protocol: ","type":"text"},{"type":"codeVoice","code":"UIGestureRecognizerRepresentable"}],"type":"paragraph"}]},{"content":[{"type":"paragraph","inlineContent":[{"type":"text","text":"See "},{"identifier":"https:\/\/developer.apple.com\/wwdc24\/10144","type":"reference","isActive":true},{"type":"text","text":" for adoption advice"}]}]}],"type":"unorderedList"},{"text":"Enhancements","type":"heading","level":1,"anchor":"Enhancements"},{"text":"Automatic trait tracking","type":"heading","level":2,"anchor":"Automatic-trait-tracking"},{"items":[{"content":[{"type":"paragraph","inlineContent":[{"text":"It’s now easier to use traits and handle changes","type":"text"}]}]},{"content":[{"type":"paragraph","inlineContent":[{"text":"View and view controller update methods now track which traits are used","type":"text"}]}]},{"content":[{"inlineContent":[{"text":"When any of the used traits change value, UIKit automatically performs an associated invalidation","type":"text"}],"type":"paragraph"}]},{"content":[{"inlineContent":[{"type":"text","text":"For example, if "},{"type":"codeVoice","code":"layoutSubviews()"},{"type":"text","text":" implementation accesses "},{"type":"codeVoice","code":"horizontalSizeClass"},{"type":"text","text":" trait, there is no need to call "},{"type":"codeVoice","code":"setNeedsLayout"},{"type":"text","text":" manually – it will be called by the automatic trait tracking system for you"}],"type":"paragraph"}]}],"type":"unorderedList"},{"text":"List improvements","type":"heading","level":2,"anchor":"List-improvements"},{"items":[{"content":[{"inlineContent":[{"type":"text","text":"Updating cells is now easier"}],"type":"paragraph"}]},{"content":[{"inlineContent":[{"type":"text","text":"All views in "},{"type":"codeVoice","code":"UICollectionView"},{"type":"text","text":"s and "},{"type":"codeVoice","code":"UITableView"},{"type":"text","text":"s now have the "},{"type":"codeVoice","code":"UITraitCollection.listEnvironment"},{"type":"text","text":" trait set."}],"type":"paragraph"}]},{"content":[{"inlineContent":[{"type":"text","text":"Use the trait to style your cells"}],"type":"paragraph"}]},{"content":[{"type":"paragraph","inlineContent":[{"type":"text","text":"With this, you don’t need to know the style of the list at the time of configuration of a cell"}]}]}],"type":"unorderedList"},{"text":"Update link","type":"heading","level":2,"anchor":"Update-link"},{"items":[{"content":[{"inlineContent":[{"text":"Similar to ","type":"text"},{"code":"CADisplayLink","type":"codeVoice"},{"text":", but has more features, like view tracking, as well as the ability to use low latency mode and better performance","type":"text"}],"type":"paragraph"}]}],"type":"unorderedList"},{"type":"codeListing","syntax":"swift","code":["let updateLink = UIUpdateLink(","    view: view,","    actionTarget: self,","    selector: #selector(update)",")"]},{"items":[{"content":[{"inlineContent":[{"text":"Activates automatically when the associated view is added to a visible window, and invalidates when removed","type":"text"}],"type":"paragraph"}]}],"type":"unorderedList"},{"text":"Symbol animations","type":"heading","level":2,"anchor":"Symbol-animations"},{"items":[{"content":[{"type":"paragraph","inlineContent":[{"text":"SF Symbols and UIKit have 3 new animation presets: ","type":"text"},{"code":".wiggle","type":"codeVoice"},{"text":", ","type":"text"},{"code":".breathe","type":"codeVoice"},{"text":", ","type":"text"},{"code":".rotate","type":"codeVoice"}]}]}],"type":"unorderedList"},{"type":"paragraph","inlineContent":[{"type":"image","identifier":"new-symbol-effects"}]},{"items":[{"content":[{"type":"paragraph","inlineContent":[{"type":"text","text":"New periodic behavior allows to repeat animations a set number of times, or continuously"}]}]},{"content":[{"type":"paragraph","inlineContent":[{"type":"codeVoice","code":".replace"},{"text":" now seamlessly animates badges and slashes using Magic replace, and automatically falls back to existing behavior if needed","type":"text"}]}]},{"content":[{"inlineContent":[{"text":"Watch ","type":"text"},{"identifier":"https:\/\/developer.apple.com\/wwdc24\/10188","type":"reference","isActive":true},{"text":" and ","type":"text"},{"identifier":"https:\/\/developer.apple.com\/wwdc23\/10258","type":"reference","isActive":true}],"type":"paragraph"}]}],"type":"unorderedList"},{"text":"Sensory feedback","type":"heading","level":2,"anchor":"Sensory-feedback"},{"items":[{"content":[{"inlineContent":[{"type":"text","text":"Sensory feedback is supported on iPad with Apple Pencil Pro and Magic Keyboard"}],"type":"paragraph"},{"type":"unorderedList","items":[{"content":[{"inlineContent":[{"code":"UIFeedbackGenerator","type":"codeVoice"},{"text":" supports these interactions","type":"text"}],"type":"paragraph"}]},{"content":[{"inlineContent":[{"type":"text","text":"New: "},{"code":"UICanvasFeedbackGenerator","type":"codeVoice"},{"type":"text","text":", which is perfect for drawing and canvases"}],"type":"paragraph"}]}]}]},{"content":[{"inlineContent":[{"text":"You should now pass the location within the view where the feedback has occurred","type":"text"}],"type":"paragraph"},{"type":"unorderedList","items":[{"content":[{"type":"paragraph","inlineContent":[{"type":"text","text":"Provide the context to "},{"type":"codeVoice","code":"UICanvasFeedbackGenerator"},{"type":"text","text":" using the "},{"type":"codeVoice","code":"alignmentOccurred(at:)"},{"type":"text","text":" method"}]}]}]}]}],"type":"unorderedList"},{"text":"Text improvements","type":"heading","level":2,"anchor":"Text-improvements"},{"items":[{"content":[{"type":"paragraph","inlineContent":[{"text":"New formatting panel","type":"text"}]}]},{"content":[{"inlineContent":[{"code":"UITextView","type":"codeVoice"},{"type":"text","text":"s that support rich text automatically support the new panel via a new Edit menu action"}],"type":"paragraph"},{"items":[{"content":[{"inlineContent":[{"type":"text","text":"Set "},{"type":"codeVoice","code":"allowsEditingTextAttributes"},{"type":"text","text":" to "},{"type":"codeVoice","code":"true"}],"type":"paragraph"}]}],"type":"unorderedList"}]},{"content":[{"type":"paragraph","inlineContent":[{"type":"text","text":"Developers can customize the formatting panel and disable features"}]}]},{"content":[{"type":"paragraph","inlineContent":[{"text":"Text highlighting is supported by default by ","type":"text"},{"type":"codeVoice","code":"UITextView"},{"text":" subclasses that support rich text","type":"text"}]},{"type":"unorderedList","items":[{"content":[{"type":"paragraph","inlineContent":[{"text":"Controlled by attributed string attributes (","type":"text"},{"type":"codeVoice","code":".textHighlight"},{"text":" and ","type":"text"},{"type":"codeVoice","code":".textHighlightColorScheme"},{"text":")","type":"text"}]}]}]}]}],"type":"unorderedList"},{"text":"Writing Tools","type":"heading","level":2,"anchor":"Writing-Tools"},{"items":[{"content":[{"type":"paragraph","inlineContent":[{"type":"text","text":"Text views get the new Writing Tools UI by default"}]}]},{"content":[{"inlineContent":[{"type":"text","text":"There are new APIs to customize the behavior"}],"type":"paragraph"}]}],"type":"unorderedList"},{"text":"Menu actions","type":"heading","level":2,"anchor":"Menu-actions"},{"items":[{"content":[{"inlineContent":[{"type":"text","text":"With iOS 18, menu actions are more useful for iPhone only apps"}],"type":"paragraph"}]},{"content":[{"inlineContent":[{"type":"codeVoice","code":"UICommand"},{"type":"text","text":", "},{"type":"codeVoice","code":"UIKeyCommand"},{"type":"text","text":", and "},{"type":"codeVoice","code":"UIAction"},{"type":"text","text":" can be invoked by the system for automation"}],"type":"paragraph"}]}],"type":"unorderedList"},{"text":"Apple Pencil","type":"heading","level":2,"anchor":"Apple-Pencil"},{"items":[{"content":[{"type":"paragraph","inlineContent":[{"code":"PKToolPicker","type":"codeVoice"},{"text":" now lets you define the available tools","type":"text"}]}]},{"content":[{"type":"paragraph","inlineContent":[{"text":"New APIs for building custom tools into the tool picker","type":"text"}]}]}],"type":"unorderedList"},{"text":"Written By","type":"heading","level":2,"anchor":"Written-By"},{"numberOfColumns":5,"type":"row","columns":[{"size":1,"content":[{"inlineContent":[{"identifier":"philptr","type":"image"}],"type":"paragraph"}]},{"size":4,"content":[{"level":3,"type":"heading","text":"Phil Zakharchenko","anchor":"Phil-Zakharchenko"},{"inlineContent":[{"isActive":true,"type":"reference","overridingTitle":"Contributed Notes","overridingTitleInlineContent":[{"text":"Contributed Notes","type":"text"}],"identifier":"doc:\/\/WWDCNotes\/documentation\/WWDCNotes\/philptr"},{"type":"text","text":" "},{"type":"text","text":"|"},{"type":"text","text":" "},{"isActive":true,"type":"reference","identifier":"https:\/\/github.com\/philptr"},{"type":"text","text":" "},{"type":"text","text":"|"},{"type":"text","text":" "},{"isActive":true,"type":"reference","identifier":"https:\/\/"},{"type":"text","text":" "},{"type":"text","text":"|"},{"type":"text","text":" "},{"isActive":true,"type":"reference","identifier":"https:\/\/x.com\/philzet"}],"type":"paragraph"}]}]},{"type":"paragraph","inlineContent":[{"text":"Missing anything? Corrections? ","type":"text"},{"identifier":"https:\/\/wwdcnotes.com\/documentation\/wwdcnotes\/contributing","isActive":true,"type":"reference"}]},{"text":"Related Sessions","type":"heading","level":2,"anchor":"Related-Sessions"},{"items":["doc:\/\/WWDCNotes\/documentation\/WWDCNotes\/WWDC24-10147-Elevate-your-tab-and-sidebar-experience-in-iPadOS","doc:\/\/WWDCNotes\/documentation\/WWDCNotes\/WWDC24-10145-Enhance-your-UI-animations-and-transitions","doc:\/\/WWDCNotes\/documentation\/WWDCNotes\/WWDC24-10144-Whats-new-in-SwiftUI","doc:\/\/WWDCNotes\/documentation\/WWDCNotes\/WWDC24-10188-Whats-new-in-SF-Symbols-6","doc:\/\/WWDCNotes\/documentation\/WWDCNotes\/WWDC23-10258-Animate-symbols-in-your-app","doc:\/\/WWDCNotes\/documentation\/WWDCNotes\/WWDC21-10057-Take-your-iPad-apps-to-the-next-level","doc:\/\/WWDCNotes\/documentation\/WWDCNotes\/WWDC24-10214-Squeeze-the-most-out-of-Apple-Pencil"],"type":"links","style":"list"},{"type":"small","inlineContent":[{"type":"strong","inlineContent":[{"type":"text","text":"Legal Notice"}]}]},{"type":"small","inlineContent":[{"text":"All content copyright © 2012 – 2024 Apple Inc. All rights reserved.","type":"text"},{"text":" ","type":"text"},{"text":"Swift, the Swift logo, Swift Playgrounds, Xcode, Instruments, Cocoa Touch, Touch ID, FaceID, iPhone, iPad, Safari, Apple Vision, Apple Watch, App Store, iPadOS, watchOS, visionOS, tvOS, Mac, and macOS are trademarks of Apple Inc., registered in the U.S. and other countries.","type":"text"},{"text":" ","type":"text"},{"text":"This website is not made by, affiliated with, nor endorsed by Apple.","type":"text"}]}]}],"metadata":{"title":"What’s new in UIKit","modules":[{"name":"WWDC Notes"}],"roleHeading":"WWDC24","role":"sampleCode"},"sections":[],"schemaVersion":{"patch":0,"major":0,"minor":3},"references":{"doc://WWDCNotes/documentation/WWDCNotes/philptr":{"type":"topic","title":"Phil Zakharchenko (5 notes)","kind":"article","abstract":[{"type":"text","text":"macOS UI & Frameworks | previously AppKit @ Apple"}],"identifier":"doc:\/\/WWDCNotes\/documentation\/WWDCNotes\/philptr","role":"sampleCode","images":[{"type":"card","identifier":"philptr.jpeg"},{"type":"icon","identifier":"philptr.jpeg"}],"url":"\/documentation\/wwdcnotes\/philptr"},"doc://WWDCNotes/documentation/WWDCNotes/WWDC24-10188-Whats-new-in-SF-Symbols-6":{"type":"topic","title":"What’s new in SF Symbols 6","kind":"article","abstract":[{"type":"text","text":"Explore the latest updates to SF Symbols, Apple’s library of iconography designed to integrate seamlessly with San Francisco, the system font for all Apple platforms. Learn how the new Wiggle, Rotate, and Breathe animation presets can bring vitality to your interface. To get the most out of this session, we recommend first watching “What’s new in SF Symbols 5” from WWDC23."}],"identifier":"doc:\/\/WWDCNotes\/documentation\/WWDCNotes\/WWDC24-10188-Whats-new-in-SF-Symbols-6","role":"sampleCode","url":"\/documentation\/wwdcnotes\/wwdc24-10188-whats-new-in-sf-symbols-6"},"https://x.com/philzet":{"type":"link","title":"X\/Twitter","titleInlineContent":[{"type":"text","text":"X\/Twitter"}],"identifier":"https:\/\/x.com\/philzet","url":"https:\/\/x.com\/philzet"},"doc://WWDCNotes/documentation/WWDCNotes/WWDC21-10057-Take-your-iPad-apps-to-the-next-level":{"type":"topic","title":"Take your iPad apps to the next level","kind":"article","abstract":[{"type":"text","text":"Make even better iPad apps: Learn how you can adopt prominent scenes for uninterrupted, focused interactions. Help people stay engaged and fast with keyboard shortcuts and the keyboard shortcut interface. Explore how the latest in pointer enhancements can help your app boost productivity."}],"identifier":"doc:\/\/WWDCNotes\/documentation\/WWDCNotes\/WWDC21-10057-Take-your-iPad-apps-to-the-next-level","role":"sampleCode","url":"\/documentation\/wwdcnotes\/wwdc21-10057-take-your-ipad-apps-to-the-next-level"},"https://developer.apple.com/wwdc24/10144":{"type":"link","title":"What’s new in SwiftUI","titleInlineContent":[{"type":"text","text":"What’s new in SwiftUI"}],"identifier":"https:\/\/developer.apple.com\/wwdc24\/10144","url":"https:\/\/developer.apple.com\/wwdc24\/10144"},"philptr":{"type":"image","variants":[{"traits":["1x","light"],"url":"\/images\/philptr.jpeg"}],"identifier":"philptr","alt":"Profile image of Phil Zakharchenko"},"document-launch-experience":{"type":"image","variants":[{"traits":["1x","light"],"url":"\/images\/document-launch-experience.jpg"}],"identifier":"document-launch-experience","alt":"The launch view for document-based apps has a new design"},"philptr.jpeg":{"type":"image","variants":[{"traits":["1x","light"],"url":"\/images\/philptr.jpeg"}],"identifier":"philptr.jpeg","alt":null},"https://developer.apple.com/wwdc24/10188":{"type":"link","title":"What’s new in SF Symbols 6","titleInlineContent":[{"type":"text","text":"What’s new in SF Symbols 6"}],"identifier":"https:\/\/developer.apple.com\/wwdc24\/10188","url":"https:\/\/developer.apple.com\/wwdc24\/10188"},"new-symbol-effects":{"type":"image","variants":[{"traits":["1x","light"],"url":"\/images\/new-symbol-effects.jpg"}],"identifier":"new-symbol-effects","alt":"3 new animation presets in iOS 18"},"doc://WWDCNotes/documentation/WWDCNotes/WWDC23-10258-Animate-symbols-in-your-app":{"type":"topic","title":"Animate symbols in your app","kind":"article","abstract":[{"type":"text","text":"Bring delight to your app with animated symbols. Explore the new Symbols framework, which features a unified API to create and configure symbol effects. Learn how SwiftUI, AppKit, and UIKit make it easy to animate symbols in user interfaces. Discover tips and tricks to seamlessly integrate the new animations alongside other app content. To get the most from this session, we recommend first watching “What’s new in SF Symbols 5.”"}],"identifier":"doc:\/\/WWDCNotes\/documentation\/WWDCNotes\/WWDC23-10258-Animate-symbols-in-your-app","role":"sampleCode","url":"\/documentation\/wwdcnotes\/wwdc23-10258-animate-symbols-in-your-app"},"WWDCNotes.png":{"type":"image","variants":[{"traits":["1x","light"],"url":"\/images\/WWDCNotes.png"}],"identifier":"WWDCNotes.png","alt":null},"doc://WWDCNotes/documentation/WWDCNotes/WWDC24-10144-Whats-new-in-SwiftUI":{"type":"topic","title":"What’s new in SwiftUI","kind":"article","abstract":[{"type":"text","text":"Learn how you can use SwiftUI to build great apps for any Apple platform. Explore a fresh new look and feel for tabs and documents on iPadOS. Improve your window management with new windowing APIs, and gain more control over immersive spaces and volumes in your visionOS apps. We’ll also take you through other exciting refinements that help you make expressive charts, customize and layout text, and so much more."}],"identifier":"doc:\/\/WWDCNotes\/documentation\/WWDCNotes\/WWDC24-10144-Whats-new-in-SwiftUI","role":"sampleCode","url":"\/documentation\/wwdcnotes\/wwdc24-10144-whats-new-in-swiftui"},"https://wwdcnotes.com/documentation/wwdcnotes/contributing":{"type":"link","title":"Contributions are welcome!","titleInlineContent":[{"type":"text","text":"Contributions are welcome!"}],"identifier":"https:\/\/wwdcnotes.com\/documentation\/wwdcnotes\/contributing","url":"https:\/\/wwdcnotes.com\/documentation\/wwdcnotes\/contributing"},"https://":{"type":"link","title":"Blog","titleInlineContent":[{"type":"text","text":"Blog"}],"identifier":"https:\/\/","url":"https:\/\/"},"https://developer.apple.com/wwdc24/10132":{"type":"link","title":"Evolve your document launch experience","titleInlineContent":[{"type":"text","text":"Evolve your document launch experience"}],"identifier":"https:\/\/developer.apple.com\/wwdc24\/10132","url":"https:\/\/developer.apple.com\/wwdc24\/10132"},"https://developer.apple.com/wwdc24/10118":{"type":"download","identifier":"https:\/\/developer.apple.com\/wwdc24\/10118","url":"https:\/\/developer.apple.com\/wwdc24\/10118","checksum":null},"doc://WWDCNotes/documentation/WWDCNotes/WWDC24":{"title":"WWDC24","role":"collectionGroup","abstract":[{"type":"text","text":"Xcode 16, Swift 6, iOS 18, macOS 15 (Sequoia), tvOS 18, visionOS 2, watchOS 11."},{"type":"text","text":" "},{"type":"text","text":"New APIs: Swift Testing, "},{"code":"FinanceKit","type":"codeVoice"},{"type":"text","text":", "},{"code":"TabletopKit","type":"codeVoice"},{"type":"text","text":", and more."}],"images":[{"identifier":"WWDC24-Icon.png","type":"icon"},{"identifier":"WWDC24.jpeg","type":"card"}],"url":"\/documentation\/wwdcnotes\/wwdc24","type":"topic","kind":"article","identifier":"doc:\/\/WWDCNotes\/documentation\/WWDCNotes\/WWDC24"},"WWDC24-Icon.png":{"type":"image","variants":[{"traits":["1x","light"],"url":"\/images\/WWDC24-Icon.png"}],"identifier":"WWDC24-Icon.png","alt":null},"https://developer.apple.com/wwdc24/10147":{"type":"link","title":"Elevate your tab and sidebar experience in iPadOS","titleInlineContent":[{"type":"text","text":"Elevate your tab and sidebar experience in iPadOS"}],"identifier":"https:\/\/developer.apple.com\/wwdc24\/10147","url":"https:\/\/developer.apple.com\/wwdc24\/10147"},"https://developer.apple.com/wwdc23/10258":{"type":"link","title":"Animate symbols in your app","titleInlineContent":[{"type":"text","text":"Animate symbols in your app"}],"identifier":"https:\/\/developer.apple.com\/wwdc23\/10258","url":"https:\/\/developer.apple.com\/wwdc23\/10258"},"WWDC24.jpeg":{"type":"image","variants":[{"traits":["1x","light"],"url":"\/images\/WWDC24.jpeg"}],"identifier":"WWDC24.jpeg","alt":null},"doc://WWDCNotes/documentation/WWDCNotes/WWDC24-10145-Enhance-your-UI-animations-and-transitions":{"type":"topic","title":"Enhance your UI animations and transitions","kind":"article","abstract":[{"type":"text","text":"Explore how to adopt the zoom transition in navigation and presentations to increase the sense of continuity in your app, and learn how to animate UIKit views with SwiftUI animations to make it easier to build animations that feel continuous."}],"identifier":"doc:\/\/WWDCNotes\/documentation\/WWDCNotes\/WWDC24-10145-Enhance-your-UI-animations-and-transitions","role":"sampleCode","url":"\/documentation\/wwdcnotes\/wwdc24-10145-enhance-your-ui-animations-and-transitions"},"doc://WWDCNotes/documentation/WWDCNotes":{"kind":"symbol","images":[{"identifier":"WWDCNotes.png","type":"icon"}],"type":"topic","identifier":"doc:\/\/WWDCNotes\/documentation\/WWDCNotes","abstract":[{"type":"text","text":"Session notes shared by the community for the community."}],"url":"\/documentation\/wwdcnotes","role":"collection","title":"WWDC Notes"},"doc://WWDCNotes/documentation/WWDCNotes/WWDC24-10214-Squeeze-the-most-out-of-Apple-Pencil":{"type":"topic","title":"Squeeze the most out of Apple Pencil","kind":"article","abstract":[{"type":"text","text":"New in iOS 18, iPadOS 18, and visionOS 2, the PencilKit tool picker gains the ability to have completely custom tools, with custom attributes. Learn how to express your custom drawing experience in the tool picker using the same great tool picking experience available across the system. Discover how to access the new features of the Apple Pencil Pro, including roll angle, the squeeze gesture, and haptic feedback."}],"identifier":"doc:\/\/WWDCNotes\/documentation\/WWDCNotes\/WWDC24-10214-Squeeze-the-most-out-of-Apple-Pencil","role":"sampleCode","url":"\/documentation\/wwdcnotes\/wwdc24-10214-squeeze-the-most-out-of-apple-pencil"},"https://github.com/philptr":{"type":"link","title":"GitHub","titleInlineContent":[{"type":"text","text":"GitHub"}],"identifier":"https:\/\/github.com\/philptr","url":"https:\/\/github.com\/philptr"},"doc://WWDCNotes/documentation/WWDCNotes/WWDC24-10147-Elevate-your-tab-and-sidebar-experience-in-iPadOS":{"type":"topic","title":"Elevate your tab and sidebar experience in iPadOS","kind":"article","abstract":[{"type":"text","text":"iPadOS 18 introduces a new navigation system that gives people the flexibility to choose between using a tab bar or sidebar. The newly redesigned tab bar provides more space for content and other functionality. Learn how to use SwiftUI and UIKit to enable customization features – like adding, removing and reordering tabs – to enable a more personal touch in your app."}],"identifier":"doc:\/\/WWDCNotes\/documentation\/WWDCNotes\/WWDC24-10147-Elevate-your-tab-and-sidebar-experience-in-iPadOS","role":"sampleCode","url":"\/documentation\/wwdcnotes\/wwdc24-10147-elevate-your-tab-and-sidebar-experience-in-ipados"}}}